crappy_multitasking.cpython-38-x86_64-linux-gnu.so
crappy_python_multitasking-0.1.0.dist-info/top_level.txt
crappy_python_multitasking-0.1.0.dist-info/METADATA
crappy_python_multitasking-0.1.0.dist-info/RECORD
crappy_python_multitasking-0.1.0.dist-info/LICENSE
crappy_python_multitasking-0.1.0.dist-info/WHEEL
